{
    "type": "FeatureCollection",
    "features": [
        {
            "type": "Feature",
            "properties": {
                "county": "臺南市",
                "name": "山上區公所",
                "phone": "06-5781801",
                "address": "臺南市山上區南洲里南洲325號"
            },
            "geometry": {
                "type": "Point",
                "coordinates": [
                    120.352718,
                    23.103563
                ]
            }
        },
        {
            "type": "Feature",
            "properties": {
                "county": "臺南市",
                "name": "山上國中",
                "phone": "06-7021578#13",
                "address": "臺南市山上區山上里山上130號"
            },
            "geometry": {
                "type": "Point",
                "coordinates": [
                    120.358324,
                    23.103317
                ]
            }
        },
        {
            "type": "Feature",
            "properties": {
                "county": "臺南市",
                "name": "南洲里農民教育活動中心",
                "phone": "06-5782045",
                "address": "臺南市山上區南洲里南洲197號"
            },
            "geometry": {
                "type": "Point",
                "coordinates": [
                    120.353431,
                    23.101392
                ]
            }
        },
        {
            "type": "Feature",
            "properties": {
                "county": "臺南市",
                "name": "山上國小",
                "phone": "06-5781203#830",
                "address": "臺南市山上區南洲里南洲42號"
            },
            "geometry": {
                "type": "Point",
                "coordinates": [
                    120.355531,
                    23.101112
                ]
            }
        },
        {
            "type": "Feature",
            "properties": {
                "county": "臺南市",
                "name": "新莊里大庄活動中心",
                "phone": "06-5782011",
                "address": "臺南市山上區新莊里大庄32號"
            },
            "geometry": {
                "type": "Point",
                "coordinates": [
                    120.354461,
                    23.094389
                ]
            }
        },
        {
            "type": "Feature",
            "properties": {
                "county": "臺南市",
                "name": "平陽里活動中心",
                "phone": "06-5782726",
                "address": "臺南市山上區平陽里石子崎48號"
            },
            "geometry": {
                "type": "Point",
                "coordinates": [
                    120.38056,
                    23.087097
                ]
            }
        },
        {
            "type": "Feature",
            "properties": {
                "county": "臺南市",
                "name": "山上里農民教育活動中心",
                "phone": "06-5782138",
                "address": "臺南市山上區山上里山上134-1號"
            },
            "geometry": {
                "type": "Point",
                "coordinates": [
                    120.357722,
                    23.102032
                ]
            }
        },
        {
            "type": "Feature",
            "properties": {
                "county": "臺南市",
                "name": "豐德里活動中心",
                "phone": "06-5782235",
                "address": "臺南市山上區豐德里隙子口49-2號"
            },
            "geometry": {
                "type": "Point",
                "coordinates": [
                    120.361121,
                    23.077369
                ]
            }
        }
    ]
}